tekinstr/__init__.py
tekinstr/common.py
tekinstr/dvm.py
tekinstr/filesystem.py
tekinstr/instrument.py
tekinstr/measurement.py
tekinstr/model.py
tekinstr/oscilloscope.py
tekinstr/spectrum_analyzer.py
tekinstr/trigger.py
tekinstr/version.py
tekinstr/mdo3000/__init__.py
tekinstr/mdo3000/dvm.py
tekinstr/mdo3000/filesysystem.py
tekinstr/mdo3000/mdo3000.py
tekinstr/mdo3000/oscilloscope.py
tekinstr/mdo3000/spectrum_analyzer.py
tekinstr/mdo3000/trigger.py
tekinstr/mso4000/__init__.py
tekinstr/mso4000/filesystem.py
tekinstr/mso4000/mso4000.py
tekinstr/mso4000/oscilloscope.py
tekinstr/mso4000/trigger.py
tekinstr/mso4000b/__init__.py
tekinstr/mso4000b/filesystem.py
tekinstr/mso4000b/mso4000b.py
tekinstr/mso4000b/oscilloscope.py
tekinstr/mso4000b/trigger.py
tekinstr/tds3000/__init__.py
tekinstr/tds3000/oscilloscope.py
tekinstr/tds3000/tds3000.py
tekinstr/tds3000/trigger.py
waveformDT/__init__.py
waveformDT/test_wdt.py
waveformDT/waveform.py
tekinstr-1.0.24.dist-info/LICENSE
tekinstr-1.0.24.dist-info/METADATA
tekinstr-1.0.24.dist-info/WHEEL
tekinstr-1.0.24.dist-info/top_level.txt
tekinstr-1.0.24.dist-info/RECORD
