Metadata-Version: 2.1
Name: tekinstr
Version: 1.0.24
Summary: Communication with Tektronix oscilloscopes
Home-page: https://github.com/l-johnston/tekinstr
Author: Lee Johnston
Author-email: lee.johnston.100@gmail.com
License: MIT
Platform: UNKNOWN
Classifier: Programming Language :: Python :: 3
Classifier: Topic :: Scientific/Engineering
Classifier: License :: OSI Approved :: MIT License
Classifier: Intended Audience :: Science/Research
Requires-Dist: numpy
Requires-Dist: sympy
Requires-Dist: matplotlib
Requires-Dist: unyt
Requires-Dist: pyvisa
